{
	"version": "1.2",
	"copyright": "(C) Copyright IBM Corp. 2011",
	"data": [{
		"id": "dS",
		"fields": [{
			"id": "fX",
			"label": "coordinate value"
		},
		{
			"id": "fC",
			"label": "color value"
		}],
		"rows": [[18,
		57]]
	}],
	"grammar": [{
		"coordinates": {
			"dimensions": [{
				"scale": {
					"spans": [{
						"max": 100.0,
						"min": 0.0
					}]
				}
			}],
			"style": {
				"fill": {
					"type": "linear",
					"angle": 225.0,
					"colors": [{
						"color": {
							"b": 0,
							"g": 0,
							"r": 0
						},
						"offset": 0
					},
					{
						"color": {
							"b": 255,
							"g": 255,
							"r": 255
						},
						"offset": 0.25
					},
					{
						"color": {
							"b": 0,
							"g": 0,
							"r": 0
						},
						"offset": 0.75
					}]
				},
				"outline": {
					"b": 0,
					"g": 0,
					"r": 0
				}
			}
		},
		"elements": [{
			"type": "interval",
			"data": {
				"$ref": "dS"
			},
			"position": [{
				"field": {
					"$ref": "fX"
				}
			}],
			"color": [{
				"field": {
					"$ref": "fC"
				},
				"scale": {
					"spans": [{
						"max": 100.0,
						"min": 0.0
					}]
				},
				"mapping": [{
					"color": {
						"a": 0.5,
						"b": 255,
						"g": 0,
						"r": 0
					},
					"offset": 0.0
				},
				{
					"color": {
						"b": 0,
						"g": 255,
						"r": 255
					},
					"offset": 1.0
				}]
			}],
			"style": {
				"outline": {
					"b": 0,
					"g": 68,
					"r": 0
				}
			}
		}]
	}]
}