{
  "data": [
    {
      "id": "data",
      "fields": [
        {"id": "_VOIDS_FIELD_", "label": "_VOIDS_FIELD_"},
        {
          "id": "_SERIES_FIELD_",
          "label": "Product line",
          "categories": [
            "Camping Equipment",
            "Golf Equipment",
            "Mountaineering Equipment",
            "Outdoor Protection",
            "Personal Accessories"
          ]
        },
        {"id": "_VALUES_FIELD_", "label": "Revenue"}
      ],
      "rows": [
        [ null, 0, 8.971399092E7 ],
        [ null, 1, 2.590546558E7 ],
        [ null, 2, 2.08913506E7 ],
        [ null, 3, 3171114.92 ],
        [ null, 4, 3.189446586E7 ]
      ]
    }
  ],
  "grammar": [
    {
      "coordinates": {
        "dimensions": [
          {
            "scale": {
              "spans": [
                {
                  "min": 0,
                  "max": 8.971399092E7,
                  "fit": "nice"
                }
              ]
            },
            "axis": {
              "gridStyle": {
                "fill": "rgba(128,128,128,0.40)",
                "stroke": {"width": "1px", "style": "solid"}
              },
              "lineStyle": {"fill": "transparent"},
              "markStyle": {"fill": "transparent"},
              "tickStyle": {
                "fill": "rgba(97,97,97,1.0)",
                "font": {
                  "family": "Arial",
                  "size": "8pt",
                  "weight": "normal",
                  "style": "normal"
                }
              },
              "title": [ {"$ref": "_VALUES_FIELD_"} ],
              "titleStyle": {
                "fill": "rgba(97,97,97,1.0)",
                "font": {
                  "family": "Arial",
                  "size": "8pt",
                  "weight": "normal",
                  "style": "normal"
                }
              }
            }
          },
          {
            "axis": {
              "lineStyle": {
                "fill": "rgba(97,97,97,1.0)",
                "stroke": {"width": "1px", "cap": "square"}
              },
              "markStyle": {
                "fill": "transparent",
                "stroke": {"width": "1px", "cap": "square"}
              },
              "tickStyle": {},
              "titleStyle": {
                "fill": "rgba(97,97,97,1.0)",
                "font": {
                  "family": "Arial",
                  "size": "8pt",
                  "weight": "normal",
                  "style": "normal"
                }
              }
            }
          },
          {"scale": {"local": true}}
        ]
      },
      "elements": [
        {
          "type": "interval",
          "position": [
            {"field": {"$ref": "_VALUES_FIELD_"}},
            {"field": {"$ref": "_SERIES_FIELD_"}},
            {"field": {"$ref": "_SERIES_FIELD_"}}
          ],
          "color": [
            {
              "id": "_PALETTE_",
              "field": {"$ref": "_SERIES_FIELD_"},
              "modifies": "both",
              "palette": [
                "rgba(58,112,207,1.0)",
                "rgba(110,201,212,1.0)",
                "rgba(219,116,13,1.0)",
                "rgba(222,171,18,1.0)",
                "rgba(35,138,32,1.0)",
                "rgba(113,196,12,1.0)",
                "rgba(118,59,161,1.0)",
                "rgba(150,129,230,1.0)",
                "rgba(145,102,26,1.0)",
                "rgba(214,214,34,1.0)",
                "rgba(162,44,15,1.0)",
                "rgba(229,95,64,1.0)",
                "rgba(112,152,181,1.0)",
                "rgba(197,209,212,1.0)"
              ]
            }
          ],
          "style": {
            "fill": {
              "type": "linear",
              "angle": 0,
              "colors": [
                {
                  "color": {
                    "dAlpha": 0,
                    "dSaturation": 0,
                    "dValue": 0.1
                  },
                  "offset": 0.04
                },
                {
                  "color": {
                    "dAlpha": 0,
                    "dSaturation": 0,
                    "dValue": -0.1
                  },
                  "offset": 1
                }
              ],
              "global": false
            },
            "stroke": {"width": "1px", "style": "solid"},
            "outline": {"dValue": -0.25},
            "outlineMethod": "inside"
          }
        }
      ]
    }
  ],
  "legendPosition": "right",
  "legends": [
    {
      "bounds": {"width": "25%"},
      "content": [
        {
          "aesthetics": [
            {"aesthetic": {"$ref": "_PALETTE_"}}
          ],
          "layout": {"reverse": false},
          "local": false,
          "swatchBoxStyle": {
            "fill": "transparent",
            "stroke": {"width": "1px", "style": "solid"},
            "outline": "rgba(0,0,128,1.0)",
            "outlineMethod": "inside",
            "size": "16px"
          },
          "swatchStyle": {
            "stroke": {"width": 0},
            "outlineMethod": "inside",
            "padding": {"bottom": 2, "right": 4},
            "size": "14px"
          },
          "textStyle": {
            "fill": "rgba(97,97,97,1.0)",
            "font": {
              "family": "Arial",
              "size": "8pt",
              "weight": "normal",
              "style": "normal"
            },
            "valign": "middleOfFirstLine"
          }
        }
      ],
      "style": {
        "fill": "transparent",
        "align": "middle",
        "padding": {"left": 4},
        "valign": "start"
      }
    }
  ],
  "size": {"width": 500, "height": 350},
  "version": "1.2"
}